python_topsis/Topsis_Shikha_101903629.py
python_topsis/__init__.py
Topsis_Shikha_101903629-0.0.0.dist-info/LICENSE
Topsis_Shikha_101903629-0.0.0.dist-info/METADATA
Topsis_Shikha_101903629-0.0.0.dist-info/WHEEL
Topsis_Shikha_101903629-0.0.0.dist-info/top_level.txt
Topsis_Shikha_101903629-0.0.0.dist-info/RECORD
