Metadata-Version: 2.1
Name: Topsis-Shikha-101903629
Version: 0.0.0
Summary: TOPSIS Implementation using Python
Author: ShikhaShikha
Author-email: sshikha_be19@thapar.edu
License: UNKNOWN
Keywords: python,topsis python,calculate topsis score,TOPSIS,topsis using python
Platform: UNKNOWN
Classifier: Development Status :: 1 - Planning
Classifier: Intended Audience :: Developers
Classifier: Programming Language :: Python :: 3
Classifier: Operating System :: Unix
Classifier: Operating System :: MacOS :: MacOS X
Classifier: Operating System :: Microsoft :: Windows
License-File: LICENSE
